sdot/Cell.py
sdot/CellFunction.py
sdot/ConvexFunction.py
sdot/D2GTransportMap.py
sdot/Expr.py
sdot/G2DTransportMap.py
sdot/PoomVec.py
sdot/PowerDiagram.py
sdot/PowerDiagramSummary.py
sdot/SdotPlan.py
sdot/TransformationMatrix.py
sdot/VtkOutput.py
sdot/__init__.py
sdot/optimal_transport_plan.py
sdot/bindings/RefMap.h
sdot/bindings/TF_objects.SConstruct
sdot/bindings/TF_objects_bindings.cpp
sdot/bindings/__init__.py
sdot/bindings/construct.py
sdot/bindings/generic_objects.SConstruct
sdot/bindings/generic_objects_bindings.cpp
sdot/bindings/img_interpolation.SConstruct
sdot/bindings/img_interpolation_bindings.cpp
sdot/bindings/integration.SConstruct
sdot/bindings/integration_bindings.cpp
sdot/bindings/integration_module.py
sdot/bindings/loader.py
sdot/bindings/poom_vec_nd_0.SConstruct
sdot/bindings/poom_vec_nd_0_bindings.cpp
sdot/bindings/poom_vec_nd_1.SConstruct
sdot/bindings/poom_vec_nd_1_bindings.cpp
sdot/bindings/sdot.SConstruct
sdot/bindings/sdot_bindings.cpp
sdot/bindings/cpp/.DS_Store
sdot/bindings/cpp/sdot/Cell.cxx
sdot/bindings/cpp/sdot/Cell.h
sdot/bindings/cpp/sdot/Cut.cxx
sdot/bindings/cpp/sdot/Cut.h
sdot/bindings/cpp/sdot/CutType.h
sdot/bindings/cpp/sdot/acceleration_structures/AccelerationStructure.h
sdot/bindings/cpp/sdot/acceleration_structures/AffineTransformation.h
sdot/bindings/cpp/sdot/acceleration_structures/CellTraversalError.h
sdot/bindings/cpp/sdot/acceleration_structures/LowCountAccelerationStructure.cxx
sdot/bindings/cpp/sdot/acceleration_structures/LowCountAccelerationStructure.h
sdot/bindings/cpp/sdot/acceleration_structures/RegularGrid.cxx
sdot/bindings/cpp/sdot/acceleration_structures/VoronoiAccelerationStructure.cxx
sdot/bindings/cpp/sdot/acceleration_structures/VoronoiAccelerationStructure.h
sdot/bindings/cpp/sdot/distributions/ConstantValue.h
sdot/bindings/cpp/sdot/local_weight_bounds/LocalWeightBounds.h
sdot/bindings/cpp/sdot/local_weight_bounds/LocalWeightBounds_ConstantValue.h
sdot/bindings/cpp/sdot/poom/PoomVec.cxx
sdot-2024.12.7.1.dist-info/WHEEL
sdot-2024.12.7.1.dist-info/METADATA
sdot-2024.12.7.1.dist-info/RECORD
