Metadata-Version: 2.3
Name: sdot
Version: 2024.12.7.1
Summary: Tools to construct/handle PowerDiagram, notably for semi-discrete optimal transport
Keywords: optimal transport,power diagram,Laguerre diagram
Author-email: Hugo Leclerc <hugo.leclerc@universite-paris-saclay.fr>
Requires-Dist: munch
Requires-Dist: pybind11
Requires-Dist: archspec
Requires-Dist: scons
Requires-Dist: pytest
Requires-Dist: numpy
Requires-Dist: matplotlib
Requires-Dist: dload
Requires-Dist: gitpython
Requires-Dist: scipy
